{
  "episode_id": "40",
  "start_pose": {
    "start_position": [
      -66.93987083364662,
      58.10016202571461,
      -10.0
    ],
    "start_quaternionr": [
      0.0,
      0.0,
      0.45500295271640373,
      0.8904899286456608
    ]
  },
  "info": {
    "geodesic_distance": 72,
    "euclidean_distance": 47.4007
  },
  "map_name": "WesternTown_test",
  "true_name": " Climber",
  "object_name": "SM_Climber01_272",
  "pose": [
    [
      -28.72185516357422,
      31.28394889831543,
      1.1912304162979126
    ]
  ],
  "size": " mid(3.5*2.0=7.0 squares)",
  "description": " Rectangular overhead frame structure, metal texture with evenly spaced yellow rungs and vertical support poles, designed for climbing or swinging in playground environments.",
  "category": "",
  "used-in-train": 1,
  "commonsenible": 1
}