{
  "episode_id": "57",
  "start_pose": {
    "start_position": [
      318.64161941385544,
      450.992436728434,
      -7.800000011920929
    ],
    "start_quaternionr": [
      0.0,
      0.0,
      0.9625001896065466,
      0.2712810074578789
    ]
  },
  "info": {
    "geodesic_distance": 54,
    "euclidean_distance": 36.8109
  },
  "map_name": "NYC_test",
  "true_name": "Climber",
  "object_name": "SM_Climber01_62",
  "pose": [
    [
      287.1000061035156,
      469.29998779296875,
      0.19999998807907104
    ]
  ],
  "size": "big(3.75*1=3.75 squares)",
  "description": "Geometric rectangular frame, black vertical supports with yellow overhead rungs, open ladder-like construction with sturdy build, used for climbing or physical training activities.",
  "category": "",
  "used-in-train": 1,
  "commonsenible": 1
}