{
  "episode_id": "4",
  "start_pose": {
    "start_position": [
      -87.29710298066792,
      229.06316214642425,
      -10.0
    ],
    "start_quaternionr": [
      0.0,
      0.0,
      0.865023131062974,
      0.5017319829610315
    ]
  },
  "info": {
    "geodesic_distance": 84,
    "euclidean_distance": 50.7481
  },
  "map_name": "BrushifyRoad_test",
  "true_name": " Wheelbarrow",
  "object_name": "SM_WheelBarrow_01_23",
  "pose": [
    [
      -57.12769317626953,
      245.10374450683594,
      30.52165985107422
    ]
  ],
  "size": " small(2.0*1.25=2.5 squares)",
  "description": " Rectangular wooden container with a single front wheel and two extended handles, aged wood texture, used for transporting small loads manually.",
  "category": "",
  "used-in-train": 1,
  "commonsenible": 1
}