{
  "episode_id": "17",
  "start_pose": {
    "start_position": [
      1253.3470018096432,
      -311.6843687932914,
      -10.0
    ],
    "start_quaternionr": [
      0.0,
      0.0,
      0.5267607307704857,
      0.8500136072546979
    ]
  },
  "info": {
    "geodesic_distance": 35,
    "euclidean_distance": 25.0104
  },
  "map_name": "BrushifyUrban_test",
  "true_name": "Dog",
  "object_name": "cane_corso_eat_anim_46",
  "pose": [
    [
      1258.199951171875,
      -334.6999816894531,
      1.5
    ]
  ],
  "size": "small(1.25*0.75=0.94 squares)",
  "description": "Organic quadruped shape, short dark fur, muscular body with upright sitting posture and alert ears, consistent with guarding or companion animal.",
  "category": "",
  "used-in-train": 1,
  "commonsenible": 1
}