{
  "episode_id": "28",
  "start_pose": {
    "start_position": [
      61.21314191695183,
      0.7684988119120533,
      -10.0
    ],
    "start_quaternionr": [
      0.0,
      0.0,
      0.9824204728443159,
      -0.18668158595949091
    ]
  },
  "info": {
    "geodesic_distance": 57,
    "euclidean_distance": 43.7194
  },
  "map_name": "Slum_test",
  "true_name": " Barrel",
  "object_name": "SM_Steel_Barrel_23",
  "pose": [
    [
      19.462324142456055,
      12.770683288574219,
      -2.0799977779388428
    ]
  ],
  "size": " small(0.75*0.75=0.56 squares)",
  "description": " Cylindrical shape, dark red metal surface, visible cap on one side, typically used for liquid or material storage.",
  "category": "",
  "used-in-train": 0,
  "commonsenible": 1
}