{
  "episode_id": "66",
  "start_pose": {
    "start_position": [
      69.08703806214693,
      19.36031841238529,
      -6.600000023841858
    ],
    "start_quaternionr": [
      0.0,
      0.0,
      0.9998995171309509,
      -0.014175882381392911
    ]
  },
  "info": {
    "geodesic_distance": 54,
    "euclidean_distance": 32.4553
  },
  "map_name": "NYC_test",
  "true_name": "Car",
  "object_name": "SM_Sedan_01a6",
  "pose": [
    [
      100.5999984741211,
      25.299999237060547,
      1.399999976158142
    ]
  ],
  "size": "mid(4.5*2.0=9.0 squares)",
  "description": "Compact four-door sedan, metallic blue exterior with tinted windows and rear spoiler, sleek profile with standard alloy wheels, designed for personal transportation.",
  "category": "",
  "used-in-train": 1,
  "commonsenible": 1
}