{
  "episode_id": "14",
  "start_pose": {
    "start_position": [
      -723.3930331461602,
      -99.63774653788842,
      -10.0
    ],
    "start_quaternionr": [
      0.0,
      0.0,
      0.9998240091089888,
      -0.01876035205502974
    ]
  },
  "info": {
    "geodesic_distance": 71,
    "euclidean_distance": 45.9306
  },
  "map_name": "CityPark_test",
  "true_name": "Dog",
  "object_name": "celtic_wolfhound_bark_anim_24",
  "pose": [
    [
      -761.5999755859375,
      -76.5,
      3.6999998092651367
    ]
  ],
  "size": "small(2.0*1.25=2.5 squares)",
  "description": "Organic quadruped shape, short dark fur, elongated body with alert stance and raised tail, consistent with companion or working animal.",
  "category": "",
  "used-in-train": 1,
  "commonsenible": 1
}